litho1pt0/__init__.py
litho1pt0/documentation.py
litho1pt0/Notebooks/litho1pt0/Ex1-Litho1Layers.ipynb
litho1pt0/Notebooks/litho1pt0/Ex2-Litho1Properties.ipynb
litho1pt0/Notebooks/litho1pt0/Ex3-CrustalRegionalisation.ipynb
litho1pt0/Notebooks/litho1pt0/WorkEx1-CratonAverageProperties.ipynb
litho1pt0/Notebooks/litho1pt0/WorkEx2-OceanDepthAge.ipynb
litho1pt0/Notebooks/litho1pt0/data/age.3.6.nc
litho1pt0/data/Crust1pt0-regionalisation.npz
litho1pt0/data/litho_data.npz
litho1pt0-1.5.0.dist-info/COPYING
litho1pt0-1.5.0.dist-info/COPYING.LESSER
litho1pt0-1.5.0.dist-info/LICENCE
litho1pt0-1.5.0.dist-info/METADATA
litho1pt0-1.5.0.dist-info/WHEEL
litho1pt0-1.5.0.dist-info/top_level.txt
litho1pt0-1.5.0.dist-info/RECORD
