Metadata-Version: 2.1
Name: litho1pt0
Version: 1.5.0
Summary: Python interface to Litho 1.0 dataset - based on stripy
Home-page: https://github.com/underworldcode/litho1pt0
Author: LM
Author-email: louis.moresi@unimelb.edu.au
License: UNKNOWN
Platform: UNKNOWN
Requires-Dist: stripy
